sockapp/__init__.py
sockapp/app.py
sockapp/constants.py
sockapp/run_app.py
sockapp/receiver/__init__.py
sockapp/receiver/receiver.py
sockapp/receiver/tcp_file_receiver.py
sockapp/receiver/tcp_message_receiver.py
sockapp/receiver/udp_file_receiver.py
sockapp/receiver/udp_message_receiver.py
sockapp/sender/__init__.py
sockapp/sender/sender.py
sockapp/sender/tcp_file_sender.py
sockapp/sender/tcp_message_sender.py
sockapp/sender/udp_file_sender.py
sockapp/sender/udp_message_sender.py
sockapp/static/css/styles.css
sockapp/static/js/info.js
sockapp/static/js/jquery.min.js
sockapp/static/js/main.js
sockapp/static/js/messaging.js
sockapp/static/js/nav.js
sockapp/static/js/sweetalert.min.js
sockapp/templates/index.html
sockapp/templates/messaging.html
sockapp/templates/nav.html
sockapp/templates/components/info.html
sockapp/templates/components/nav.html
sockapp/utils/__init__.py
sockapp/utils/error.py
sockapp/utils/file_dir_helpers.py
sockapp/utils/ip_helpers.py
sockapp/utils/path_helpers.py
sockapp-0.1a8.dist-info/LICENSE
sockapp-0.1a8.dist-info/METADATA
sockapp-0.1a8.dist-info/WHEEL
sockapp-0.1a8.dist-info/entry_points.txt
sockapp-0.1a8.dist-info/top_level.txt
sockapp-0.1a8.dist-info/RECORD
